moth/__init__.py
moth/log.py
moth/cli/__init__.py
moth/driver/__init__.py
moth/message/__init__.py
moth/message/exceptions.py
moth/server/__init__.py
starmoth-0.11.0.dist-info/METADATA
starmoth-0.11.0.dist-info/WHEEL
starmoth-0.11.0.dist-info/entry_points.txt
starmoth-0.11.0.dist-info/top_level.txt
starmoth-0.11.0.dist-info/RECORD
