Metadata-Version: 2.2
Name: starmoth
Version: 0.11.0
Summary: A small wrapper library to help test systems using STAR
Author: Gudjon Magnusson
Author-email: gmagnusson@fraunhofer.org
License: proprietary
Keywords: Fraunhofer,STAR,testing
Requires-Python: >=3.7, <4
Requires-Dist: pyzmq>=25.0.0
Requires-Dist: numpy>=1.14.5
Requires-Dist: msgpack>=1.0.4
Requires-Dist: colorlog>=6.0.0
Dynamic: author
Dynamic: author-email
Dynamic: description
Dynamic: description-content-type
Dynamic: keywords
Dynamic: license
Dynamic: requires-dist
Dynamic: requires-python
Dynamic: summary
